{
  "points": [
    {
      "x": 976.34,
      "y": 284.9,
      "id": 0
    },
    {
      "x": 548.58,
      "y": 819.56,
      "id": 1
    },
    {
      "x": 450.48,
      "y": 275.23,
      "id": 2
    },
    {
      "x": 184.88,
      "y": 597.81,
      "id": 3
    },
    {
      "x": 468.3,
      "y": 19.86,
      "id": 4
    },
    {
      "x": 690.08,
      "y": 728.07,
      "id": 5
    },
    {
      "x": 324.34,
      "y": 965.87,
      "id": 6
    },
    {
      "x": 468.09,
      "y": 75.25,
      "id": 7
    },
    {
      "x": 456.06,
      "y": 825.92,
      "id": 8
    },
    {
      "x": 690.76,
      "y": 522.43,
      "id": 9
    },
    {
      "x": 643.23,
      "y": 741.64,
      "id": 10
    },
    {
      "x": 479.11,
      "y": 152.1,
      "id": 11
    },
    {
      "x": 400.87,
      "y": 141.29,
      "id": 12
    },
    {
      "x": 684.14,
      "y": 967.47,
      "id": 13
    },
    {
      "x": 105.68,
      "y": 983.11,
      "id": 14
    },
    {
      "x": 474.98,
      "y": 487.86,
      "id": 15
    },
    {
      "x": 854.54,
      "y": 106.41,
      "id": 16
    },
    {
      "x": 590.61,
      "y": 962.45,
      "id": 17
    },
    {
      "x": 744.47,
      "y": 351.52,
      "id": 18
    },
    {
      "x": 868.13,
      "y": 506.6,
      "id": 19
    },
    {
      "x": 21.51,
      "y": 829.46,
      "id": 20
    },
    {
      "x": 881.78,
      "y": 277.93,
      "id": 21
    },
    {
      "x": 412.55,
      "y": 944.91,
      "id": 22
    },
    {
      "x": 861.68,
      "y": 575.18,
      "id": 23
    },
    {
      "x": 769.96,
      "y": 794.82,
      "id": 24
    },
    {
      "x": 816.13,
      "y": 15.06,
      "id": 25
    },
    {
      "x": 401.69,
      "y": 847.7,
      "id": 26
    },
    {
      "x": 440.97,
      "y": 733.04,
      "id": 27
    },
    {
      "x": 636.44,
      "y": 939.72,
      "id": 28
    },
    {
      "x": 341.73,
      "y": 861.67,
      "id": 29
    },
    {
      "x": 11.12,
      "y": 921.42,
      "id": 30
    },
    {
      "x": 881.58,
      "y": 307.91,
      "id": 31
    },
    {
      "x": 849.03,
      "y": 118.07,
      "id": 32
    },
    {
      "x": 990.56,
      "y": 507.83,
      "id": 33
    },
    {
      "x": 674.82,
      "y": 465.88,
      "id": 34
    },
    {
      "x": 324.55,
      "y": 226.63,
      "id": 35
    },
    {
      "x": 178.44,
      "y": 811.34,
      "id": 36
    },
    {
      "x": 239.84,
      "y": 430.7,
      "id": 37
    },
    {
      "x": 850.39,
      "y": 245.32,
      "id": 38
    },
    {
      "x": 657.21,
      "y": 797.3,
      "id": 39
    },
    {
      "x": 388.92,
      "y": 197.56,
      "id": 40
    },
    {
      "x": 646.19,
      "y": 653.34,
      "id": 41
    },
    {
      "x": 288.81,
      "y": 630.7,
      "id": 42
    },
    {
      "x": 844.78,
      "y": 725.99,
      "id": 43
    },
    {
      "x": 787.03,
      "y": 873.5,
      "id": 44
    },
    {
      "x": 471.87,
      "y": 132.29,
      "id": 45
    },
    {
      "x": 478.09,
      "y": 409.28,
      "id": 46
    },
    {
      "x": 683.19,
      "y": 922.14,
      "id": 47
    },
    {
      "x": 293.85,
      "y": 623.06,
      "id": 48
    },
    {
      "x": 124.14,
      "y": 617.23,
      "id": 49
    },
    {
      "x": 382.71,
      "y": 114.06,
      "id": 50
    },
    {
      "x": 497.41,
      "y": 407.95,
      "id": 51
    },
    {
      "x": 748.74,
      "y": 140.11,
      "id": 52
    },
    {
      "x": 856.5,
      "y": 672.51,
      "id": 53
    },
    {
      "x": 251.28,
      "y": 274.74,
      "id": 54
    },
    {
      "x": 640.9,
      "y": 218.65,
      "id": 55
    },
    {
      "x": 569.49,
      "y": 725.06,
      "id": 56
    },
    {
      "x": 693.53,
      "y": 810.16,
      "id": 57
    },
    {
      "x": 915.63,
      "y": 386.52,
      "id": 58
    },
    {
      "x": 569.0,
      "y": 989.67,
      "id": 59
    },
    {
      "x": 39.13,
      "y": 76.13,
      "id": 60
    },
    {
      "x": 753.0,
      "y": 954.91,
      "id": 61
    },
    {
      "x": 67.39,
      "y": 134.57,
      "id": 62
    },
    {
      "x": 73.36,
      "y": 846.06,
      "id": 63
    },
    {
      "x": 414.71,
      "y": 217.7,
      "id": 64
    },
    {
      "x": 727.47,
      "y": 226.8,
      "id": 65
    },
    {
      "x": 395.08,
      "y": 903.63,
      "id": 66
    },
    {
      "x": 227.28,
      "y": 920.05,
      "id": 67
    },
    {
      "x": 368.89,
      "y": 766.07,
      "id": 68
    },
    {
      "x": 472.82,
      "y": 608.1,
      "id": 69
    },
    {
      "x": 433.03,
      "y": 700.6,
      "id": 70
    },
    {
      "x": 144.22,
      "y": 230.8,
      "id": 71
    },
    {
      "x": 115.71,
      "y": 954.02,
      "id": 72
    },
    {
      "x": 985.53,
      "y": 879.9,
      "id": 73
    },
    {
      "x": 513.2,
      "y": 160.03,
      "id": 74
    },
    {
      "x": 353.83,
      "y": 981.37,
      "id": 75
    },
    {
      "x": 812.11,
      "y": 440.09,
      "id": 76
    },
    {
      "x": 622.08,
      "y": 107.4,
      "id": 77
    },
    {
      "x": 547.64,
      "y": 669.29,
      "id": 78
    },
    {
      "x": 972.01,
      "y": 119.43,
      "id": 79
    },
    {
      "x": 686.13,
      "y": 950.8,
      "id": 80
    },
    {
      "x": 571.7,
      "y": 665.75,
      "id": 81
    },
    {
      "x": 725.85,
      "y": 116.7,
      "id": 82
    },
    {
      "x": 309.23,
      "y": 121.92,
      "id": 83
    },
    {
      "x": 357.2,
      "y": 178.32,
      "id": 84
    },
    {
      "x": 973.0,
      "y": 126.87,
      "id": 85
    },
    {
      "x": 887.78,
      "y": 733.34,
      "id": 86
    },
    {
      "x": 670.82,
      "y": 242.09,
      "id": 87
    },
    {
      "x": 772.35,
      "y": 647.31,
      "id": 88
    },
    {
      "x": 925.22,
      "y": 389.97,
      "id": 89
    },
    {
      "x": 542.98,
      "y": 10.86,
      "id": 90
    },
    {
      "x": 179.28,
      "y": 447.11,
      "id": 91
    },
    {
      "x": 879.27,
      "y": 893.51,
      "id": 92
    },
    {
      "x": 16.74,
      "y": 512.13,
      "id": 93
    },
    {
      "x": 719.05,
      "y": 590.75,
      "id": 94
    },
    {
      "x": 20.99,
      "y": 225.87,
      "id": 95
    },
    {
      "x": 98.12,
      "y": 586.74,
      "id": 96
    },
    {
      "x": 138.66,
      "y": 548.62,
      "id": 97
    },
    {
      "x": 653.56,
      "y": 368.1,
      "id": 98
    },
    {
      "x": 246.87,
      "y": 696.74,
      "id": 99
    },
    {
      "x": 527.11,
      "y": 879.11,
      "id": 100
    },
    {
      "x": 146.06,
      "y": 275.78,
      "id": 101
    },
    {
      "x": 447.63,
      "y": 598.52,
      "id": 102
    },
    {
      "x": 165.0,
      "y": 318.93,
      "id": 103
    },
    {
      "x": 805.3,
      "y": 164.98,
      "id": 104
    },
    {
      "x": 82.34,
      "y": 853.15,
      "id": 105
    },
    {
      "x": 954.82,
      "y": 268.93,
      "id": 106
    },
    {
      "x": 388.57,
      "y": 302.28,
      "id": 107
    },
    {
      "x": 422.01,
      "y": 162.46,
      "id": 108
    },
    {
      "x": 277.81,
      "y": 835.26,
      "id": 109
    },
    {
      "x": 561.4,
      "y": 918.13,
      "id": 110
    },
    {
      "x": 827.98,
      "y": 771.59,
      "id": 111
    },
    {
      "x": 985.35,
      "y": 7.5,
      "id": 112
    },
    {
      "x": 52.25,
      "y": 619.58,
      "id": 113
    },
    {
      "x": 688.17,
      "y": 560.75,
      "id": 114
    },
    {
      "x": 536.11,
      "y": 159.23,
      "id": 115
    },
    {
      "x": 501.38,
      "y": 182.83,
      "id": 116
    },
    {
      "x": 805.81,
      "y": 368.2,
      "id": 117
    },
    {
      "x": 34.07,
      "y": 808.17,
      "id": 118
    },
    {
      "x": 596.7,
      "y": 477.75,
      "id": 119
    },
    {
      "x": 401.15,
      "y": 651.34,
      "id": 120
    },
    {
      "x": 74.38,
      "y": 789.58,
      "id": 121
    },
    {
      "x": 418.39,
      "y": 168.88,
      "id": 122
    },
    {
      "x": 726.53,
      "y": 22.27,
      "id": 123
    },
    {
      "x": 199.53,
      "y": 46.29,
      "id": 124
    },
    {
      "x": 103.72,
      "y": 86.42,
      "id": 125
    },
    {
      "x": 455.67,
      "y": 159.22,
      "id": 126
    },
    {
      "x": 839.96,
      "y": 497.17,
      "id": 127
    },
    {
      "x": 737.98,
      "y": 134.79,
      "id": 128
    },
    {
      "x": 512.5,
      "y": 864.86,
      "id": 129
    },
    {
      "x": 966.98,
      "y": 27.03,
      "id": 130
    },
    {
      "x": 739.57,
      "y": 249.88,
      "id": 131
    },
    {
      "x": 218.45,
      "y": 399.65,
      "id": 132
    },
    {
      "x": 332.17,
      "y": 221.74,
      "id": 133
    },
    {
      "x": 770.32,
      "y": 610.54,
      "id": 134
    },
    {
      "x": 176.37,
      "y": 961.76,
      "id": 135
    },
    {
      "x": 315.98,
      "y": 678.3,
      "id": 136
    },
    {
      "x": 705.97,
      "y": 102.33,
      "id": 137
    },
    {
      "x": 543.36,
      "y": 705.01,
      "id": 138
    },
    {
      "x": 963.69,
      "y": 651.14,
      "id": 139
    },
    {
      "x": 960.72,
      "y": 145.56,
      "id": 140
    },
    {
      "x": 202.36,
      "y": 667.7,
      "id": 141
    },
    {
      "x": 715.31,
      "y": 642.2,
      "id": 142
    },
    {
      "x": 996.91,
      "y": 71.5,
      "id": 143
    },
    {
      "x": 78.8,
      "y": 476.23,
      "id": 144
    },
    {
      "x": 537.65,
      "y": 933.26,
      "id": 145
    },
    {
      "x": 685.14,
      "y": 363.95,
      "id": 146
    },
    {
      "x": 203.75,
      "y": 659.19,
      "id": 147
    },
    {
      "x": 105.96,
      "y": 709.73,
      "id": 148
    },
    {
      "x": 99.98,
      "y": 2.35,
      "id": 149
    },
    {
      "x": 223.11,
      "y": 759.2,
      "id": 150
    },
    {
      "x": 684.05,
      "y": 463.11,
      "id": 151
    },
    {
      "x": 589.0,
      "y": 495.25,
      "id": 152
    },
    {
      "x": 954.25,
      "y": 780.47,
      "id": 153
    },
    {
      "x": 15.74,
      "y": 915.83,
      "id": 154
    },
    {
      "x": 724.99,
      "y": 706.49,
      "id": 155
    },
    {
      "x": 435.83,
      "y": 985.72,
      "id": 156
    },
    {
      "x": 262.51,
      "y": 700.72,
      "id": 157
    },
    {
      "x": 993.65,
      "y": 717.26,
      "id": 158
    },
    {
      "x": 926.96,
      "y": 448.36,
      "id": 159
    },
    {
      "x": 715.13,
      "y": 482.87,
      "id": 160
    },
    {
      "x": 281.32,
      "y": 897.22,
      "id": 161
    },
    {
      "x": 500.13,
      "y": 576.18,
      "id": 162
    },
    {
      "x": 862.96,
      "y": 690.65,
      "id": 163
    },
    {
      "x": 262.67,
      "y": 264.56,
      "id": 164
    },
    {
      "x": 632.32,
      "y": 332.16,
      "id": 165
    },
    {
      "x": 773.19,
      "y": 694.29,
      "id": 166
    },
    {
      "x": 296.12,
      "y": 551.25,
      "id": 167
    },
    {
      "x": 965.69,
      "y": 317.34,
      "id": 168
    },
    {
      "x": 48.53,
      "y": 966.89,
      "id": 169
    },
    {
      "x": 150.3,
      "y": 870.95,
      "id": 170
    },
    {
      "x": 656.48,
      "y": 341.81,
      "id": 171
    },
    {
      "x": 90.86,
      "y": 129.3,
      "id": 172
    },
    {
      "x": 776.35,
      "y": 156.69,
      "id": 173
    },
    {
      "x": 479.25,
      "y": 706.62,
      "id": 174
    },
    {
      "x": 280.65,
      "y": 620.18,
      "id": 175
    },
    {
      "x": 138.22,
      "y": 355.04,
      "id": 176
    },
    {
      "x": 928.38,
      "y": 762.41,
      "id": 177
    },
    {
      "x": 429.04,
      "y": 170.72,
      "id": 178
    },
    {
      "x": 56.92,
      "y": 86.48,
      "id": 179
    },
    {
      "x": 161.88,
      "y": 733.01,
      "id": 180
    },
    {
      "x": 585.86,
      "y": 243.18,
      "id": 181
    },
    {
      "x": 690.32,
      "y": 986.6,
      "id": 182
    },
    {
      "x": 565.28,
      "y": 363.36,
      "id": 183
    },
    {
      "x": 40.41,
      "y": 655.08,
      "id": 184
    },
    {
      "x": 438.43,
      "y": 691.25,
      "id": 185
    },
    {
      "x": 848.71,
      "y": 349.33,
      "id": 186
    },
    {
      "x": 143.04,
      "y": 47.2,
      "id": 187
    },
    {
      "x": 712.08,
      "y": 579.17,
      "id": 188
    },
    {
      "x": 681.03,
      "y": 628.26,
      "id": 189
    },
    {
      "x": 16.88,
      "y": 675.05,
      "id": 190
    },
    {
      "x": 843.02,
      "y": 29.59,
      "id": 191
    },
    {
      "x": 941.58,
      "y": 698.79,
      "id": 192
    },
    {
      "x": 719.38,
      "y": 954.75,
      "id": 193
    },
    {
      "x": 503.08,
      "y": 402.7,
      "id": 194
    },
    {
      "x": 583.83,
      "y": 497.79,
      "id": 195
    },
    {
      "x": 776.8,
      "y": 172.13,
      "id": 196
    },
    {
      "x": 313.52,
      "y": 23.49,
      "id": 197
    },
    {
      "x": 379.05,
      "y": 379.36,
      "id": 198
    },
    {
      "x": 431.6,
      "y": 651.93,
      "id": 199
    },
    {
      "x": 470.03,
      "y": 871.85,
      "id": 200
    },
    {
      "x": 268.21,
      "y": 805.68,
      "id": 201
    },
    {
      "x": 434.66,
      "y": 211.24,
      "id": 202
    },
    {
      "x": 21.74,
      "y": 209.48,
      "id": 203
    },
    {
      "x": 617.63,
      "y": 564.55,
      "id": 204
    },
    {
      "x": 683.68,
      "y": 415.94,
      "id": 205
    },
    {
      "x": 699.76,
      "y": 204.89,
      "id": 206
    },
    {
      "x": 15.37,
      "y": 52.22,
      "id": 207
    },
    {
      "x": 208.89,
      "y": 145.45,
      "id": 208
    },
    {
      "x": 460.97,
      "y": 570.14,
      "id": 209
    },
    {
      "x": 788.03,
      "y": 520.95,
      "id": 210
    },
    {
      "x": 847.49,
      "y": 308.66,
      "id": 211
    },
    {
      "x": 138.61,
      "y": 615.04,
      "id": 212
    },
    {
      "x": 577.74,
      "y": 103.98,
      "id": 213
    },
    {
      "x": 537.53,
      "y": 214.68,
      "id": 214
    },
    {
      "x": 351.88,
      "y": 767.31,
      "id": 215
    },
    {
      "x": 726.7,
      "y": 370.49,
      "id": 216
    },
    {
      "x": 623.0,
      "y": 8.23,
      "id": 217
    },
    {
      "x": 783.53,
      "y": 86.41,
      "id": 218
    },
    {
      "x": 515.24,
      "y": 204.36,
      "id": 219
    },
    {
      "x": 150.06,
      "y": 726.69,
      "id": 220
    },
    {
      "x": 147.92,
      "y": 643.14,
      "id": 221
    },
    {
      "x": 37.58,
      "y": 927.23,
      "id": 222
    },
    {
      "x": 268.64,
      "y": 99.42,
      "id": 223
    },
    {
      "x": 414.66,
      "y": 491.95,
      "id": 224
    },
    {
      "x": 633.87,
      "y": 853.9,
      "id": 225
    },
    {
      "x": 504.73,
      "y": 33.18,
      "id": 226
    },
    {
      "x": 433.37,
      "y": 892.7,
      "id": 227
    },
    {
      "x": 402.3,
      "y": 37.93,
      "id": 228
    },
    {
      "x": 4.11,
      "y": 161.93,
      "id": 229
    },
    {
      "x": 278.77,
      "y": 126.25,
      "id": 230
    },
    {
      "x": 294.92,
      "y": 841.71,
      "id": 231
    },
    {
      "x": 855.8,
      "y": 822.26,
      "id": 232
    },
    {
      "x": 390.07,
      "y": 698.91,
      "id": 233
    },
    {
      "x": 753.82,
      "y": 969.07,
      "id": 234
    },
    {
      "x": 780.64,
      "y": 107.3,
      "id": 235
    },
    {
      "x": 293.64,
      "y": 331.01,
      "id": 236
    },
    {
      "x": 455.66,
      "y": 77.86,
      "id": 237
    },
    {
      "x": 617.52,
      "y": 170.8,
      "id": 238
    },
    {
      "x": 566.6,
      "y": 808.26,
      "id": 239
    },
    {
      "x": 264.12,
      "y": 183.61,
      "id": 240
    },
    {
      "x": 448.38,
      "y": 817.0,
      "id": 241
    },
    {
      "x": 926.41,
      "y": 347.39,
      "id": 242
    },
    {
      "x": 506.03,
      "y": 83.03,
      "id": 243
    },
    {
      "x": 369.89,
      "y": 533.59,
      "id": 244
    },
    {
      "x": 471.33,
      "y": 681.24,
      "id": 245
    },
    {
      "x": 873.43,
      "y": 806.59,
      "id": 246
    },
    {
      "x": 888.71,
      "y": 328.03,
      "id": 247
    },
    {
      "x": 63.31,
      "y": 358.73,
      "id": 248
    },
    {
      "x": 128.72,
      "y": 916.41,
      "id": 249
    },
    {
      "x": 344.33,
      "y": 517.74,
      "id": 250
    },
    {
      "x": 171.01,
      "y": 409.0,
      "id": 251
    },
    {
      "x": 214.9,
      "y": 816.3,
      "id": 252
    },
    {
      "x": 161.74,
      "y": 600.25,
      "id": 253
    },
    {
      "x": 310.53,
      "y": 942.59,
      "id": 254
    },
    {
      "x": 245.51,
      "y": 677.94,
      "id": 255
    },
    {
      "x": 367.35,
      "y": 649.39,
      "id": 256
    },
    {
      "x": 381.25,
      "y": 711.37,
      "id": 257
    },
    {
      "x": 182.16,
      "y": 80.65,
      "id": 258
    },
    {
      "x": 31.42,
      "y": 161.02,
      "id": 259
    },
    {
      "x": 34.1,
      "y": 105.28,
      "id": 260
    },
    {
      "x": 892.5,
      "y": 684.25,
      "id": 261
    },
    {
      "x": 358.93,
      "y": 343.57,
      "id": 262
    },
    {
      "x": 650.16,
      "y": 91.74,
      "id": 263
    },
    {
      "x": 857.51,
      "y": 277.75,
      "id": 264
    },
    {
      "x": 226.77,
      "y": 480.65,
      "id": 265
    },
    {
      "x": 123.05,
      "y": 189.89,
      "id": 266
    },
    {
      "x": 62.26,
      "y": 995.15,
      "id": 267
    },
    {
      "x": 205.07,
      "y": 202.36,
      "id": 268
    },
    {
      "x": 484.33,
      "y": 227.54,
      "id": 269
    },
    {
      "x": 832.5,
      "y": 737.6,
      "id": 270
    },
    {
      "x": 752.73,
      "y": 686.37,
      "id": 271
    },
    {
      "x": 102.23,
      "y": 519.32,
      "id": 272
    },
    {
      "x": 584.4,
      "y": 446.55,
      "id": 273
    },
    {
      "x": 547.53,
      "y": 353.06,
      "id": 274
    },
    {
      "x": 773.57,
      "y": 260.34,
      "id": 275
    },
    {
      "x": 780.91,
      "y": 492.13,
      "id": 276
    },
    {
      "x": 540.86,
      "y": 601.25,
      "id": 277
    },
    {
      "x": 860.14,
      "y": 968.96,
      "id": 278
    },
    {
      "x": 551.15,
      "y": 790.47,
      "id": 279
    },
    {
      "x": 679.47,
      "y": 687.44,
      "id": 280
    },
    {
      "x": 770.06,
      "y": 612.07,
      "id": 281
    },
    {
      "x": 957.92,
      "y": 958.0,
      "id": 282
    },
    {
      "x": 134.47,
      "y": 885.63,
      "id": 283
    },
    {
      "x": 595.64,
      "y": 309.26,
      "id": 284
    },
    {
      "x": 686.6,
      "y": 43.15,
      "id": 285
    },
    {
      "x": 543.21,
      "y": 523.57,
      "id": 286
    },
    {
      "x": 389.41,
      "y": 718.96,
      "id": 287
    },
    {
      "x": 791.02,
      "y": 519.87,
      "id": 288
    },
    {
      "x": 972.82,
      "y": 822.07,
      "id": 289
    },
    {
      "x": 630.41,
      "y": 833.23,
      "id": 290
    },
    {
      "x": 833.89,
      "y": 847.53,
      "id": 291
    },
    {
      "x": 969.29,
      "y": 358.69,
      "id": 292
    },
    {
      "x": 802.5,
      "y": 977.2,
      "id": 293
    },
    {
      "x": 347.02,
      "y": 1.45,
      "id": 294
    },
    {
      "x": 62.58,
      "y": 465.61,
      "id": 295
    },
    {
      "x": 612.22,
      "y": 698.91,
      "id": 296
    },
    {
      "x": 599.23,
      "y": 985.14,
      "id": 297
    },
    {
      "x": 770.95,
      "y": 733.76,
      "id": 298
    },
    {
      "x": 887.56,
      "y": 589.97,
      "id": 299
    },
    {
      "x": 163.72,
      "y": 466.06,
      "id": 300
    },
    {
      "x": 658.43,
      "y": 790.57,
      "id": 301
    },
    {
      "x": 235.75,
      "y": 971.03,
      "id": 302
    },
    {
      "x": 438.96,
      "y": 219.77,
      "id": 303
    },
    {
      "x": 163.13,
      "y": 801.51,
      "id": 304
    },
    {
      "x": 292.68,
      "y": 147.96,
      "id": 305
    },
    {
      "x": 568.83,
      "y": 144.71,
      "id": 306
    },
    {
      "x": 939.07,
      "y": 74.86,
      "id": 307
    },
    {
      "x": 544.4,
      "y": 670.6,
      "id": 308
    },
    {
      "x": 315.12,
      "y": 203.93,
      "id": 309
    },
    {
      "x": 54.75,
      "y": 633.24,
      "id": 310
    },
    {
      "x": 74.42,
      "y": 586.25,
      "id": 311
    },
    {
      "x": 952.76,
      "y": 423.28,
      "id": 312
    },
    {
      "x": 59.45,
      "y": 727.65,
      "id": 313
    },
    {
      "x": 807.92,
      "y": 72.51,
      "id": 314
    },
    {
      "x": 758.62,
      "y": 715.89,
      "id": 315
    },
    {
      "x": 942.08,
      "y": 322.7,
      "id": 316
    },
    {
      "x": 468.82,
      "y": 45.62,
      "id": 317
    },
    {
      "x": 779.21,
      "y": 440.96,
      "id": 318
    },
    {
      "x": 891.03,
      "y": 485.91,
      "id": 319
    },
    {
      "x": 239.21,
      "y": 110.31,
      "id": 320
    },
    {
      "x": 36.94,
      "y": 960.64,
      "id": 321
    },
    {
      "x": 879.7,
      "y": 314.69,
      "id": 322
    },
    {
      "x": 677.33,
      "y": 6.98,
      "id": 323
    },
    {
      "x": 860.04,
      "y": 962.77,
      "id": 324
    },
    {
      "x": 79.64,
      "y": 364.74,
      "id": 325
    },
    {
      "x": 27.63,
      "y": 106.24,
      "id": 326
    },
    {
      "x": 517.62,
      "y": 45.45,
      "id": 327
    },
    {
      "x": 759.29,
      "y": 580.72,
      "id": 328
    },
    {
      "x": 885.73,
      "y": 889.7,
      "id": 329
    },
    {
      "x": 802.57,
      "y": 906.53,
      "id": 330
    },
    {
      "x": 681.87,
      "y": 975.37,
      "id": 331
    },
    {
      "x": 916.9,
      "y": 241.04,
      "id": 332
    },
    {
      "x": 60.86,
      "y": 117.34,
      "id": 333
    },
    {
      "x": 132.72,
      "y": 258.17,
      "id": 334
    },
    {
      "x": 537.3,
      "y": 583.99,
      "id": 335
    },
    {
      "x": 732.25,
      "y": 125.08,
      "id": 336
    },
    {
      "x": 229.41,
      "y": 27.98,
      "id": 337
    },
    {
      "x": 8.56,
      "y": 608.11,
      "id": 338
    },
    {
      "x": 603.92,
      "y": 480.64,
      "id": 339
    },
    {
      "x": 554.61,
      "y": 729.4,
      "id": 340
    },
    {
      "x": 974.46,
      "y": 710.94,
      "id": 341
    },
    {
      "x": 610.11,
      "y": 32.38,
      "id": 342
    },
    {
      "x": 81.7,
      "y": 915.82,
      "id": 343
    },
    {
      "x": 161.23,
      "y": 182.65,
      "id": 344
    },
    {
      "x": 766.68,
      "y": 437.9,
      "id": 345
    },
    {
      "x": 170.33,
      "y": 678.27,
      "id": 346
    },
    {
      "x": 478.66,
      "y": 286.45,
      "id": 347
    },
    {
      "x": 966.74,
      "y": 448.27,
      "id": 348
    },
    {
      "x": 169.34,
      "y": 667.14,
      "id": 349
    },
    {
      "x": 899.93,
      "y": 457.75,
      "id": 350
    },
    {
      "x": 435.61,
      "y": 380.53,
      "id": 351
    },
    {
      "x": 934.33,
      "y": 444.35,
      "id": 352
    },
    {
      "x": 369.93,
      "y": 491.03,
      "id": 353
    },
    {
      "x": 731.8,
      "y": 825.84,
      "id": 354
    },
    {
      "x": 52.24,
      "y": 520.59,
      "id": 355
    },
    {
      "x": 456.56,
      "y": 970.81,
      "id": 356
    },
    {
      "x": 889.84,
      "y": 305.03,
      "id": 357
    },
    {
      "x": 788.25,
      "y": 6.1,
      "id": 358
    },
    {
      "x": 606.47,
      "y": 442.87,
      "id": 359
    },
    {
      "x": 461.22,
      "y": 883.18,
      "id": 360
    },
    {
      "x": 718.11,
      "y": 859.63,
      "id": 361
    },
    {
      "x": 108.51,
      "y": 342.44,
      "id": 362
    },
    {
      "x": 61.92,
      "y": 157.27,
      "id": 363
    },
    {
      "x": 986.41,
      "y": 561.3,
      "id": 364
    },
    {
      "x": 552.28,
      "y": 386.41,
      "id": 365
    },
    {
      "x": 316.61,
      "y": 890.09,
      "id": 366
    },
    {
      "x": 602.6,
      "y": 979.02,
      "id": 367
    },
    {
      "x": 42.98,
      "y": 851.73,
      "id": 368
    },
    {
      "x": 877.02,
      "y": 189.65,
      "id": 369
    },
    {
      "x": 110.75,
      "y": 842.75,
      "id": 370
    },
    {
      "x": 696.84,
      "y": 144.21,
      "id": 371
    },
    {
      "x": 986.05,
      "y": 819.51,
      "id": 372
    },
    {
      "x": 85.44,
      "y": 928.69,
      "id": 373
    },
    {
      "x": 436.64,
      "y": 6.06,
      "id": 374
    },
    {
      "x": 951.72,
      "y": 185.54,
      "id": 375
    },
    {
      "x": 575.85,
      "y": 24.63,
      "id": 376
    },
    {
      "x": 947.85,
      "y": 456.82,
      "id": 377
    },
    {
      "x": 238.37,
      "y": 613.83,
      "id": 378
    },
    {
      "x": 691.26,
      "y": 358.96,
      "id": 379
    },
    {
      "x": 258.44,
      "y": 398.4,
      "id": 380
    },
    {
      "x": 879.47,
      "y": 601.99,
      "id": 381
    },
    {
      "x": 735.95,
      "y": 986.31,
      "id": 382
    },
    {
      "x": 937.87,
      "y": 976.11,
      "id": 383
    },
    {
      "x": 6.34,
      "y": 409.88,
      "id": 384
    },
    {
      "x": 751.22,
      "y": 245.73,
      "id": 385
    },
    {
      "x": 678.48,
      "y": 975.73,
      "id": 386
    },
    {
      "x": 652.36,
      "y": 124.25,
      "id": 387
    },
    {
      "x": 487.15,
      "y": 396.36,
      "id": 388
    },
    {
      "x": 647.67,
      "y": 752.17,
      "id": 389
    },
    {
      "x": 596.79,
      "y": 983.5,
      "id": 390
    },
    {
      "x": 446.1,
      "y": 522.5,
      "id": 391
    },
    {
      "x": 974.66,
      "y": 89.93,
      "id": 392
    },
    {
      "x": 863.86,
      "y": 981.75,
      "id": 393
    },
    {
      "x": 866.8,
      "y": 864.77,
      "id": 394
    },
    {
      "x": 262.0,
      "y": 788.28,
      "id": 395
    },
    {
      "x": 554.68,
      "y": 873.59,
      "id": 396
    },
    {
      "x": 639.29,
      "y": 658.57,
      "id": 397
    },
    {
      "x": 270.7,
      "y": 405.18,
      "id": 398
    },
    {
      "x": 810.12,
      "y": 917.59,
      "id": 399
    },
    {
      "x": 105.99,
      "y": 732.94,
      "id": 400
    },
    {
      "x": 287.79,
      "y": 440.11,
      "id": 401
    },
    {
      "x": 317.3,
      "y": 118.26,
      "id": 402
    },
    {
      "x": 351.22,
      "y": 762.41,
      "id": 403
    },
    {
      "x": 211.12,
      "y": 897.91,
      "id": 404
    },
    {
      "x": 499.88,
      "y": 107.04,
      "id": 405
    },
    {
      "x": 327.77,
      "y": 290.05,
      "id": 406
    },
    {
      "x": 756.5,
      "y": 864.1,
      "id": 407
    },
    {
      "x": 74.46,
      "y": 15.44,
      "id": 408
    },
    {
      "x": 84.42,
      "y": 278.06,
      "id": 409
    },
    {
      "x": 100.92,
      "y": 340.05,
      "id": 410
    },
    {
      "x": 380.11,
      "y": 79.51,
      "id": 411
    },
    {
      "x": 449.37,
      "y": 978.77,
      "id": 412
    },
    {
      "x": 305.31,
      "y": 323.34,
      "id": 413
    },
    {
      "x": 739.42,
      "y": 261.31,
      "id": 414
    },
    {
      "x": 451.68,
      "y": 38.83,
      "id": 415
    },
    {
      "x": 623.15,
      "y": 268.03,
      "id": 416
    },
    {
      "x": 692.83,
      "y": 459.01,
      "id": 417
    },
    {
      "x": 105.08,
      "y": 890.26,
      "id": 418
    },
    {
      "x": 840.52,
      "y": 20.87,
      "id": 419
    },
    {
      "x": 732.82,
      "y": 451.59,
      "id": 420
    },
    {
      "x": 720.84,
      "y": 954.39,
      "id": 421
    },
    {
      "x": 528.37,
      "y": 234.86,
      "id": 422
    },
    {
      "x": 686.08,
      "y": 339.66,
      "id": 423
    },
    {
      "x": 383.44,
      "y": 800.3,
      "id": 424
    },
    {
      "x": 213.0,
      "y": 690.07,
      "id": 425
    },
    {
      "x": 670.64,
      "y": 535.95,
      "id": 426
    },
    {
      "x": 335.16,
      "y": 730.0,
      "id": 427
    },
    {
      "x": 749.7,
      "y": 44.71,
      "id": 428
    },
    {
      "x": 987.04,
      "y": 565.65,
      "id": 429
    },
    {
      "x": 936.19,
      "y": 162.89,
      "id": 430
    },
    {
      "x": 67.29,
      "y": 846.65,
      "id": 431
    },
    {
      "x": 40.43,
      "y": 144.73,
      "id": 432
    },
    {
      "x": 621.91,
      "y": 107.52,
      "id": 433
    },
    {
      "x": 344.6,
      "y": 498.31,
      "id": 434
    },
    {
      "x": 855.11,
      "y": 339.75,
      "id": 435
    },
    {
      "x": 898.53,
      "y": 681.98,
      "id": 436
    },
    {
      "x": 914.96,
      "y": 913.15,
      "id": 437
    },
    {
      "x": 356.23,
      "y": 573.29,
      "id": 438
    },
    {
      "x": 557.9,
      "y": 548.85,
      "id": 439
    },
    {
      "x": 938.52,
      "y": 750.92,
      "id": 440
    },
    {
      "x": 629.34,
      "y": 484.79,
      "id": 441
    },
    {
      "x": 487.22,
      "y": 304.52,
      "id": 442
    },
    {
      "x": 951.33,
      "y": 826.92,
      "id": 443
    },
    {
      "x": 117.77,
      "y": 812.03,
      "id": 444
    },
    {
      "x": 288.08,
      "y": 517.1,
      "id": 445
    },
    {
      "x": 392.43,
      "y": 695.59,
      "id": 446
    },
    {
      "x": 193.71,
      "y": 739.7,
      "id": 447
    },
    {
      "x": 416.39,
      "y": 376.51,
      "id": 448
    },
    {
      "x": 17.99,
      "y": 310.03,
      "id": 449
    },
    {
      "x": 798.64,
      "y": 658.04,
      "id": 450
    },
    {
      "x": 146.0,
      "y": 501.09,
      "id": 451
    },
    {
      "x": 991.52,
      "y": 118.8,
      "id": 452
    },
    {
      "x": 407.22,
      "y": 986.04,
      "id": 453
    },
    {
      "x": 754.66,
      "y": 787.1,
      "id": 454
    },
    {
      "x": 918.27,
      "y": 902.15,
      "id": 455
    },
    {
      "x": 365.64,
      "y": 378.45,
      "id": 456
    },
    {
      "x": 791.12,
      "y": 322.46,
      "id": 457
    },
    {
      "x": 133.02,
      "y": 663.27,
      "id": 458
    },
    {
      "x": 104.31,
      "y": 763.19,
      "id": 459
    },
    {
      "x": 937.71,
      "y": 580.01,
      "id": 460
    },
    {
      "x": 95.89,
      "y": 708.62,
      "id": 461
    },
    {
      "x": 439.0,
      "y": 414.75,
      "id": 462
    },
    {
      "x": 273.46,
      "y": 723.05,
      "id": 463
    },
    {
      "x": 449.72,
      "y": 809.24,
      "id": 464
    },
    {
      "x": 388.0,
      "y": 504.4,
      "id": 465
    },
    {
      "x": 540.37,
      "y": 128.75,
      "id": 466
    },
    {
      "x": 316.36,
      "y": 264.23,
      "id": 467
    },
    {
      "x": 507.89,
      "y": 903.03,
      "id": 468
    },
    {
      "x": 818.85,
      "y": 485.68,
      "id": 469
    },
    {
      "x": 180.2,
      "y": 424.01,
      "id": 470
    },
    {
      "x": 267.53,
      "y": 51.03,
      "id": 471
    },
    {
      "x": 206.5,
      "y": 588.48,
      "id": 472
    },
    {
      "x": 718.81,
      "y": 757.57,
      "id": 473
    },
    {
      "x": 423.79,
      "y": 352.89,
      "id": 474
    },
    {
      "x": 40.02,
      "y": 891.21,
      "id": 475
    },
    {
      "x": 684.45,
      "y": 868.62,
      "id": 476
    },
    {
      "x": 605.39,
      "y": 827.1,
      "id": 477
    },
    {
      "x": 358.06,
      "y": 982.35,
      "id": 478
    },
    {
      "x": 845.03,
      "y": 969.18,
      "id": 479
    },
    {
      "x": 578.13,
      "y": 528.53,
      "id": 480
    },
    {
      "x": 870.26,
      "y": 518.98,
      "id": 481
    },
    {
      "x": 893.78,
      "y": 985.55,
      "id": 482
    },
    {
      "x": 272.7,
      "y": 623.74,
      "id": 483
    },
    {
      "x": 883.98,
      "y": 556.5,
      "id": 484
    },
    {
      "x": 211.18,
      "y": 383.21,
      "id": 485
    },
    {
      "x": 620.07,
      "y": 325.13,
      "id": 486
    },
    {
      "x": 900.07,
      "y": 101.9,
      "id": 487
    },
    {
      "x": 448.57,
      "y": 734.1,
      "id": 488
    },
    {
      "x": 670.82,
      "y": 284.07,
      "id": 489
    },
    {
      "x": 550.61,
      "y": 30.67,
      "id": 490
    },
    {
      "x": 36.98,
      "y": 106.09,
      "id": 491
    },
    {
      "x": 978.96,
      "y": 117.93,
      "id": 492
    },
    {
      "x": 857.51,
      "y": 330.84,
      "id": 493
    },
    {
      "x": 114.51,
      "y": 547.65,
      "id": 494
    },
    {
      "x": 426.17,
      "y": 753.03,
      "id": 495
    },
    {
      "x": 345.39,
      "y": 91.45,
      "id": 496
    },
    {
      "x": 822.97,
      "y": 967.63,
      "id": 497
    },
    {
      "x": 805.36,
      "y": 107.89,
      "id": 498
    },
    {
      "x": 7.46,
      "y": 347.28,
      "id": 499
    },
    {
      "x": 129.07,
      "y": 651.33,
      "id": 500
    },
    {
      "x": 225.95,
      "y": 706.89,
      "id": 501
    },
    {
      "x": 528.64,
      "y": 492.12,
      "id": 502
    },
    {
      "x": 653.09,
      "y": 162.77,
      "id": 503
    },
    {
      "x": 230.55,
      "y": 288.73,
      "id": 504
    },
    {
      "x": 892.79,
      "y": 251.92,
      "id": 505
    },
    {
      "x": 102.93,
      "y": 762.77,
      "id": 506
    },
    {
      "x": 304.36,
      "y": 705.23,
      "id": 507
    },
    {
      "x": 263.75,
      "y": 34.64,
      "id": 508
    },
    {
      "x": 657.29,
      "y": 386.95,
      "id": 509
    },
    {
      "x": 507.09,
      "y": 387.05,
      "id": 510
    },
    {
      "x": 567.02,
      "y": 425.67,
      "id": 511
    },
    {
      "x": 994.65,
      "y": 122.67,
      "id": 512
    },
    {
      "x": 131.02,
      "y": 311.2,
      "id": 513
    },
    {
      "x": 291.27,
      "y": 173.13,
      "id": 514
    },
    {
      "x": 439.23,
      "y": 929.05,
      "id": 515
    },
    {
      "x": 146.63,
      "y": 513.9,
      "id": 516
    },
    {
      "x": 549.81,
      "y": 933.39,
      "id": 517
    },
    {
      "x": 693.27,
      "y": 176.92,
      "id": 518
    },
    {
      "x": 714.59,
      "y": 910.06,
      "id": 519
    },
    {
      "x": 235.19,
      "y": 803.01,
      "id": 520
    },
    {
      "x": 970.32,
      "y": 137.65,
      "id": 521
    },
    {
      "x": 53.18,
      "y": 673.02,
      "id": 522
    },
    {
      "x": 535.97,
      "y": 736.83,
      "id": 523
    },
    {
      "x": 327.42,
      "y": 540.25,
      "id": 524
    },
    {
      "x": 788.89,
      "y": 44.76,
      "id": 525
    },
    {
      "x": 994.74,
      "y": 42.2,
      "id": 526
    },
    {
      "x": 348.36,
      "y": 37.11,
      "id": 527
    },
    {
      "x": 514.71,
      "y": 67.88,
      "id": 528
    },
    {
      "x": 185.95,
      "y": 208.71,
      "id": 529
    },
    {
      "x": 312.59,
      "y": 124.66,
      "id": 530
    },
    {
      "x": 134.46,
      "y": 339.88,
      "id": 531
    },
    {
      "x": 413.8,
      "y": 583.87,
      "id": 532
    },
    {
      "x": 746.99,
      "y": 555.87,
      "id": 533
    },
    {
      "x": 365.33,
      "y": 251.04,
      "id": 534
    },
    {
      "x": 265.04,
      "y": 948.45,
      "id": 535
    },
    {
      "x": 423.56,
      "y": 768.48,
      "id": 536
    },
    {
      "x": 122.66,
      "y": 506.68,
      "id": 537
    },
    {
      "x": 55.05,
      "y": 701.48,
      "id": 538
    },
    {
      "x": 734.51,
      "y": 791.26,
      "id": 539
    },
    {
      "x": 817.31,
      "y": 204.74,
      "id": 540
    },
    {
      "x": 575.98,
      "y": 968.54,
      "id": 541
    },
    {
      "x": 982.36,
      "y": 770.57,
      "id": 542
    },
    {
      "x": 205.1,
      "y": 493.79,
      "id": 543
    },
    {
      "x": 752.64,
      "y": 368.57,
      "id": 544
    },
    {
      "x": 723.57,
      "y": 582.65,
      "id": 545
    },
    {
      "x": 55.16,
      "y": 356.94,
      "id": 546
    },
    {
      "x": 372.02,
      "y": 834.27,
      "id": 547
    },
    {
      "x": 234.55,
      "y": 664.52,
      "id": 548
    },
    {
      "x": 313.7,
      "y": 486.34,
      "id": 549
    },
    {
      "x": 947.26,
      "y": 448.76,
      "id": 550
    },
    {
      "x": 325.45,
      "y": 831.0,
      "id": 551
    },
    {
      "x": 609.99,
      "y": 968.96,
      "id": 552
    },
    {
      "x": 356.54,
      "y": 956.59,
      "id": 553
    },
    {
      "x": 900.11,
      "y": 342.69,
      "id": 554
    },
    {
      "x": 396.18,
      "y": 623.27,
      "id": 555
    },
    {
      "x": 892.84,
      "y": 811.87,
      "id": 556
    },
    {
      "x": 184.46,
      "y": 299.95,
      "id": 557
    },
    {
      "x": 426.02,
      "y": 483.3,
      "id": 558
    },
    {
      "x": 483.5,
      "y": 462.44,
      "id": 559
    },
    {
      "x": 221.65,
      "y": 798.56,
      "id": 560
    },
    {
      "x": 391.16,
      "y": 174.57,
      "id": 561
    },
    {
      "x": 422.77,
      "y": 936.67,
      "id": 562
    },
    {
      "x": 956.82,
      "y": 429.85,
      "id": 563
    },
    {
      "x": 488.03,
      "y": 664.56,
      "id": 564
    },
    {
      "x": 370.81,
      "y": 265.11,
      "id": 565
    },
    {
      "x": 846.58,
      "y": 79.13,
      "id": 566
    },
    {
      "x": 195.99,
      "y": 487.42,
      "id": 567
    },
    {
      "x": 217.78,
      "y": 152.44,
      "id": 568
    },
    {
      "x": 573.73,
      "y": 443.87,
      "id": 569
    },
    {
      "x": 166.68,
      "y": 606.48,
      "id": 570
    },
    {
      "x": 754.83,
      "y": 551.62,
      "id": 571
    },
    {
      "x": 25.1,
      "y": 763.48,
      "id": 572
    },
    {
      "x": 413.45,
      "y": 435.46,
      "id": 573
    },
    {
      "x": 356.76,
      "y": 765.18,
      "id": 574
    },
    {
      "x": 65.42,
      "y": 295.04,
      "id": 575
    },
    {
      "x": 692.13,
      "y": 639.86,
      "id": 576
    },
    {
      "x": 42.36,
      "y": 359.65,
      "id": 577
    },
    {
      "x": 239.35,
      "y": 20.17,
      "id": 578
    },
    {
      "x": 114.56,
      "y": 700.37,
      "id": 579
    },
    {
      "x": 296.28,
      "y": 103.68,
      "id": 580
    },
    {
      "x": 510.05,
      "y": 161.42,
      "id": 581
    },
    {
      "x": 228.7,
      "y": 806.74,
      "id": 582
    },
    {
      "x": 284.92,
      "y": 712.58,
      "id": 583
    },
    {
      "x": 224.98,
      "y": 764.48,
      "id": 584
    },
    {
      "x": 38.71,
      "y": 215.97,
      "id": 585
    },
    {
      "x": 22.45,
      "y": 258.53,
      "id": 586
    },
    {
      "x": 465.41,
      "y": 910.39,
      "id": 587
    },
    {
      "x": 171.51,
      "y": 973.66,
      "id": 588
    },
    {
      "x": 586.8,
      "y": 482.23,
      "id": 589
    },
    {
      "x": 27.5,
      "y": 856.01,
      "id": 590
    },
    {
      "x": 416.35,
      "y": 640.24,
      "id": 591
    },
    {
      "x": 932.16,
      "y": 885.57,
      "id": 592
    },
    {
      "x": 490.09,
      "y": 581.53,
      "id": 593
    },
    {
      "x": 577.26,
      "y": 355.63,
      "id": 594
    },
    {
      "x": 942.23,
      "y": 136.2,
      "id": 595
    },
    {
      "x": 123.59,
      "y": 54.62,
      "id": 596
    },
    {
      "x": 996.54,
      "y": 227.24,
      "id": 597
    },
    {
      "x": 172.94,
      "y": 543.26,
      "id": 598
    },
    {
      "x": 42.08,
      "y": 86.63,
      "id": 599
    },
    {
      "x": 464.79,
      "y": 251.56,
      "id": 600
    },
    {
      "x": 327.69,
      "y": 405.46,
      "id": 601
    },
    {
      "x": 414.68,
      "y": 707.43,
      "id": 602
    },
    {
      "x": 499.28,
      "y": 319.13,
      "id": 603
    },
    {
      "x": 673.94,
      "y": 904.56,
      "id": 604
    },
    {
      "x": 887.32,
      "y": 150.28,
      "id": 605
    },
    {
      "x": 177.5,
      "y": 279.71,
      "id": 606
    },
    {
      "x": 729.72,
      "y": 36.43,
      "id": 607
    },
    {
      "x": 651.77,
      "y": 676.01,
      "id": 608
    },
    {
      "x": 942.02,
      "y": 9.63,
      "id": 609
    },
    {
      "x": 35.7,
      "y": 257.9,
      "id": 610
    },
    {
      "x": 646.52,
      "y": 910.79,
      "id": 611
    },
    {
      "x": 929.97,
      "y": 87.48,
      "id": 612
    },
    {
      "x": 295.74,
      "y": 131.45,
      "id": 613
    },
    {
      "x": 413.56,
      "y": 394.23,
      "id": 614
    },
    {
      "x": 763.39,
      "y": 382.99,
      "id": 615
    },
    {
      "x": 166.02,
      "y": 901.33,
      "id": 616
    },
    {
      "x": 962.16,
      "y": 636.93,
      "id": 617
    },
    {
      "x": 999.01,
      "y": 866.52,
      "id": 618
    },
    {
      "x": 470.15,
      "y": 487.01,
      "id": 619
    },
    {
      "x": 719.41,
      "y": 10.85,
      "id": 620
    },
    {
      "x": 275.02,
      "y": 898.15,
      "id": 621
    },
    {
      "x": 294.94,
      "y": 883.92,
      "id": 622
    },
    {
      "x": 380.44,
      "y": 845.46,
      "id": 623
    },
    {
      "x": 152.4,
      "y": 89.16,
      "id": 624
    },
    {
      "x": 302.03,
      "y": 104.47,
      "id": 625
    },
    {
      "x": 163.08,
      "y": 707.09,
      "id": 626
    },
    {
      "x": 175.08,
      "y": 789.03,
      "id": 627
    },
    {
      "x": 202.17,
      "y": 147.68,
      "id": 628
    },
    {
      "x": 197.68,
      "y": 106.94,
      "id": 629
    },
    {
      "x": 456.78,
      "y": 699.85,
      "id": 630
    },
    {
      "x": 657.66,
      "y": 324.46,
      "id": 631
    },
    {
      "x": 248.33,
      "y": 114.8,
      "id": 632
    },
    {
      "x": 485.4,
      "y": 365.2,
      "id": 633
    },
    {
      "x": 233.93,
      "y": 859.23,
      "id": 634
    },
    {
      "x": 949.46,
      "y": 953.68,
      "id": 635
    },
    {
      "x": 171.37,
      "y": 52.84,
      "id": 636
    },
    {
      "x": 226.03,
      "y": 233.72,
      "id": 637
    },
    {
      "x": 35.77,
      "y": 347.63,
      "id": 638
    },
    {
      "x": 758.81,
      "y": 874.72,
      "id": 639
    },
    {
      "x": 61.01,
      "y": 215.46,
      "id": 640
    },
    {
      "x": 492.06,
      "y": 350.55,
      "id": 641
    },
    {
      "x": 37.25,
      "y": 238.12,
      "id": 642
    },
    {
      "x": 431.36,
      "y": 643.91,
      "id": 643
    },
    {
      "x": 731.98,
      "y": 682.12,
      "id": 644
    },
    {
      "x": 705.92,
      "y": 513.57,
      "id": 645
    },
    {
      "x": 188.35,
      "y": 104.25,
      "id": 646
    },
    {
      "x": 827.02,
      "y": 2.31,
      "id": 647
    },
    {
      "x": 939.68,
      "y": 781.26,
      "id": 648
    },
    {
      "x": 472.39,
      "y": 552.64,
      "id": 649
    },
    {
      "x": 907.89,
      "y": 378.04,
      "id": 650
    },
    {
      "x": 850.68,
      "y": 152.38,
      "id": 651
    },
    {
      "x": 443.08,
      "y": 730.45,
      "id": 652
    },
    {
      "x": 902.68,
      "y": 901.99,
      "id": 653
    },
    {
      "x": 761.69,
      "y": 549.26,
      "id": 654
    },
    {
      "x": 211.82,
      "y": 969.26,
      "id": 655
    },
    {
      "x": 968.25,
      "y": 314.47,
      "id": 656
    },
    {
      "x": 580.31,
      "y": 563.13,
      "id": 657
    },
    {
      "x": 601.58,
      "y": 661.28,
      "id": 658
    },
    {
      "x": 560.32,
      "y": 433.48,
      "id": 659
    },
    {
      "x": 374.73,
      "y": 550.72,
      "id": 660
    },
    {
      "x": 766.48,
      "y": 128.36,
      "id": 661
    },
    {
      "x": 354.26,
      "y": 934.61,
      "id": 662
    },
    {
      "x": 240.69,
      "y": 55.13,
      "id": 663
    },
    {
      "x": 407.72,
      "y": 596.94,
      "id": 664
    },
    {
      "x": 143.51,
      "y": 376.78,
      "id": 665
    },
    {
      "x": 710.07,
      "y": 69.1,
      "id": 666
    },
    {
      "x": 91.18,
      "y": 348.59,
      "id": 667
    },
    {
      "x": 984.42,
      "y": 303.76,
      "id": 668
    },
    {
      "x": 158.82,
      "y": 374.62,
      "id": 669
    },
    {
      "x": 172.08,
      "y": 187.17,
      "id": 670
    },
    {
      "x": 825.15,
      "y": 993.49,
      "id": 671
    },
    {
      "x": 657.89,
      "y": 351.73,
      "id": 672
    },
    {
      "x": 876.91,
      "y": 248.4,
      "id": 673
    },
    {
      "x": 690.22,
      "y": 349.71,
      "id": 674
    },
    {
      "x": 712.96,
      "y": 730.33,
      "id": 675
    },
    {
      "x": 56.14,
      "y": 690.22,
      "id": 676
    },
    {
      "x": 608.49,
      "y": 98.71,
      "id": 677
    },
    {
      "x": 657.68,
      "y": 683.95,
      "id": 678
    },
    {
      "x": 619.37,
      "y": 225.81,
      "id": 679
    },
    {
      "x": 617.12,
      "y": 615.06,
      "id": 680
    },
    {
      "x": 788.2,
      "y": 553.67,
      "id": 681
    },
    {
      "x": 627.26,
      "y": 880.64,
      "id": 682
    },
    {
      "x": 307.5,
      "y": 907.87,
      "id": 683
    },
    {
      "x": 236.98,
      "y": 513.69,
      "id": 684
    },
    {
      "x": 723.01,
      "y": 269.13,
      "id": 685
    },
    {
      "x": 116.22,
      "y": 555.79,
      "id": 686
    },
    {
      "x": 464.02,
      "y": 335.03,
      "id": 687
    },
    {
      "x": 880.01,
      "y": 736.05,
      "id": 688
    },
    {
      "x": 836.71,
      "y": 419.77,
      "id": 689
    },
    {
      "x": 557.11,
      "y": 134.62,
      "id": 690
    },
    {
      "x": 125.53,
      "y": 11.97,
      "id": 691
    },
    {
      "x": 581.51,
      "y": 93.99,
      "id": 692
    },
    {
      "x": 662.85,
      "y": 225.42,
      "id": 693
    },
    {
      "x": 602.61,
      "y": 877.8,
      "id": 694
    },
    {
      "x": 89.74,
      "y": 451.51,
      "id": 695
    },
    {
      "x": 825.68,
      "y": 493.38,
      "id": 696
    },
    {
      "x": 307.98,
      "y": 619.98,
      "id": 697
    },
    {
      "x": 233.97,
      "y": 680.54,
      "id": 698
    },
    {
      "x": 811.12,
      "y": 166.12,
      "id": 699
    },
    {
      "x": 78.88,
      "y": 335.17,
      "id": 700
    },
    {
      "x": 241.51,
      "y": 339.69,
      "id": 701
    },
    {
      "x": 566.53,
      "y": 981.4,
      "id": 702
    },
    {
      "x": 82.76,
      "y": 687.19,
      "id": 703
    },
    {
      "x": 724.18,
      "y": 170.11,
      "id": 704
    },
    {
      "x": 121.73,
      "y": 326.27,
      "id": 705
    },
    {
      "x": 119.29,
      "y": 843.7,
      "id": 706
    },
    {
      "x": 990.08,
      "y": 896.9,
      "id": 707
    },
    {
      "x": 129.91,
      "y": 186.67,
      "id": 708
    },
    {
      "x": 666.12,
      "y": 758.89,
      "id": 709
    },
    {
      "x": 605.28,
      "y": 79.11,
      "id": 710
    },
    {
      "x": 491.9,
      "y": 567.83,
      "id": 711
    },
    {
      "x": 827.8,
      "y": 328.7,
      "id": 712
    },
    {
      "x": 901.59,
      "y": 240.12,
      "id": 713
    },
    {
      "x": 785.73,
      "y": 228.51,
      "id": 714
    },
    {
      "x": 821.26,
      "y": 15.17,
      "id": 715
    },
    {
      "x": 75.65,
      "y": 276.69,
      "id": 716
    },
    {
      "x": 918.75,
      "y": 835.12,
      "id": 717
    },
    {
      "x": 914.02,
      "y": 24.5,
      "id": 718
    },
    {
      "x": 248.08,
      "y": 41.9,
      "id": 719
    },
    {
      "x": 654.44,
      "y": 515.24,
      "id": 720
    },
    {
      "x": 805.3,
      "y": 698.51,
      "id": 721
    },
    {
      "x": 76.24,
      "y": 213.77,
      "id": 722
    },
    {
      "x": 350.99,
      "y": 398.05,
      "id": 723
    },
    {
      "x": 552.02,
      "y": 893.12,
      "id": 724
    },
    {
      "x": 443.6,
      "y": 260.23,
      "id": 725
    },
    {
      "x": 624.9,
      "y": 694.68,
      "id": 726
    },
    {
      "x": 3.63,
      "y": 979.85,
      "id": 727
    },
    {
      "x": 255.27,
      "y": 988.12,
      "id": 728
    },
    {
      "x": 201.41,
      "y": 13.39,
      "id": 729
    },
    {
      "x": 508.34,
      "y": 927.46,
      "id": 730
    },
    {
      "x": 903.38,
      "y": 619.16,
      "id": 731
    },
    {
      "x": 268.03,
      "y": 934.89,
      "id": 732
    },
    {
      "x": 214.69,
      "y": 825.97,
      "id": 733
    },
    {
      "x": 476.22,
      "y": 462.18,
      "id": 734
    },
    {
      "x": 990.28,
      "y": 513.56,
      "id": 735
    },
    {
      "x": 348.95,
      "y": 613.63,
      "id": 736
    },
    {
      "x": 955.74,
      "y": 299.03,
      "id": 737
    },
    {
      "x": 399.15,
      "y": 727.99,
      "id": 738
    },
    {
      "x": 290.01,
      "y": 534.35,
      "id": 739
    },
    {
      "x": 738.82,
      "y": 714.3,
      "id": 740
    },
    {
      "x": 525.07,
      "y": 525.41,
      "id": 741
    },
    {
      "x": 598.21,
      "y": 698.25,
      "id": 742
    },
    {
      "x": 82.98,
      "y": 360.98,
      "id": 743
    },
    {
      "x": 97.19,
      "y": 144.83,
      "id": 744
    },
    {
      "x": 997.78,
      "y": 8.58,
      "id": 745
    },
    {
      "x": 481.19,
      "y": 599.77,
      "id": 746
    },
    {
      "x": 618.5,
      "y": 466.17,
      "id": 747
    },
    {
      "x": 653.28,
      "y": 938.79,
      "id": 748
    },
    {
      "x": 575.81,
      "y": 219.63,
      "id": 749
    },
    {
      "x": 403.41,
      "y": 266.53,
      "id": 750
    },
    {
      "x": 300.71,
      "y": 201.65,
      "id": 751
    },
    {
      "x": 174.23,
      "y": 830.71,
      "id": 752
    },
    {
      "x": 277.02,
      "y": 24.4,
      "id": 753
    },
    {
      "x": 630.59,
      "y": 514.9,
      "id": 754
    },
    {
      "x": 273.47,
      "y": 637.92,
      "id": 755
    },
    {
      "x": 777.52,
      "y": 345.95,
      "id": 756
    },
    {
      "x": 541.33,
      "y": 247.03,
      "id": 757
    },
    {
      "x": 962.1,
      "y": 6.43,
      "id": 758
    },
    {
      "x": 461.34,
      "y": 222.83,
      "id": 759
    },
    {
      "x": 883.16,
      "y": 23.91,
      "id": 760
    },
    {
      "x": 909.35,
      "y": 441.75,
      "id": 761
    },
    {
      "x": 172.45,
      "y": 864.34,
      "id": 762
    },
    {
      "x": 850.31,
      "y": 173.5,
      "id": 763
    },
    {
      "x": 870.45,
      "y": 593.34,
      "id": 764
    },
    {
      "x": 798.33,
      "y": 174.52,
      "id": 765
    },
    {
      "x": 555.4,
      "y": 773.45,
      "id": 766
    },
    {
      "x": 463.34,
      "y": 870.58,
      "id": 767
    },
    {
      "x": 316.51,
      "y": 506.72,
      "id": 768
    },
    {
      "x": 334.89,
      "y": 317.43,
      "id": 769
    },
    {
      "x": 286.98,
      "y": 872.56,
      "id": 770
    },
    {
      "x": 59.41,
      "y": 542.26,
      "id": 771
    },
    {
      "x": 832.7,
      "y": 985.46,
      "id": 772
    },
    {
      "x": 825.06,
      "y": 742.98,
      "id": 773
    },
    {
      "x": 759.73,
      "y": 979.63,
      "id": 774
    },
    {
      "x": 864.6,
      "y": 668.81,
      "id": 775
    },
    {
      "x": 889.89,
      "y": 132.1,
      "id": 776
    },
    {
      "x": 423.64,
      "y": 838.83,
      "id": 777
    },
    {
      "x": 608.65,
      "y": 669.6,
      "id": 778
    },
    {
      "x": 109.47,
      "y": 524.45,
      "id": 779
    },
    {
      "x": 437.69,
      "y": 904.05,
      "id": 780
    },
    {
      "x": 261.11,
      "y": 135.68,
      "id": 781
    },
    {
      "x": 678.78,
      "y": 97.1,
      "id": 782
    },
    {
      "x": 256.55,
      "y": 435.84,
      "id": 783
    },
    {
      "x": 956.98,
      "y": 918.5,
      "id": 784
    },
    {
      "x": 592.33,
      "y": 78.67,
      "id": 785
    },
    {
      "x": 606.42,
      "y": 858.56,
      "id": 786
    },
    {
      "x": 527.12,
      "y": 273.36,
      "id": 787
    },
    {
      "x": 657.59,
      "y": 127.74,
      "id": 788
    },
    {
      "x": 341.37,
      "y": 244.86,
      "id": 789
    },
    {
      "x": 552.48,
      "y": 415.85,
      "id": 790
    },
    {
      "x": 834.25,
      "y": 947.54,
      "id": 791
    },
    {
      "x": 106.78,
      "y": 582.19,
      "id": 792
    },
    {
      "x": 734.68,
      "y": 459.11,
      "id": 793
    },
    {
      "x": 345.78,
      "y": 228.11,
      "id": 794
    },
    {
      "x": 425.54,
      "y": 415.67,
      "id": 795
    },
    {
      "x": 790.59,
      "y": 623.95,
      "id": 796
    },
    {
      "x": 279.47,
      "y": 430.92,
      "id": 797
    },
    {
      "x": 33.62,
      "y": 647.42,
      "id": 798
    },
    {
      "x": 879.27,
      "y": 213.11,
      "id": 799
    },
    {
      "x": 808.42,
      "y": 795.24,
      "id": 800
    },
    {
      "x": 59.72,
      "y": 118.85,
      "id": 801
    },
    {
      "x": 353.43,
      "y": 621.44,
      "id": 802
    },
    {
      "x": 547.6,
      "y": 813.51,
      "id": 803
    },
    {
      "x": 445.43,
      "y": 478.69,
      "id": 804
    },
    {
      "x": 776.53,
      "y": 750.61,
      "id": 805
    },
    {
      "x": 463.72,
      "y": 679.51,
      "id": 806
    },
    {
      "x": 688.29,
      "y": 862.13,
      "id": 807
    },
    {
      "x": 790.87,
      "y": 106.95,
      "id": 808
    },
    {
      "x": 389.1,
      "y": 461.52,
      "id": 809
    },
    {
      "x": 599.55,
      "y": 530.05,
      "id": 810
    },
    {
      "x": 86.47,
      "y": 939.0,
      "id": 811
    },
    {
      "x": 578.15,
      "y": 356.79,
      "id": 812
    },
    {
      "x": 748.34,
      "y": 395.48,
      "id": 813
    },
    {
      "x": 739.4,
      "y": 253.99,
      "id": 814
    },
    {
      "x": 658.41,
      "y": 170.93,
      "id": 815
    },
    {
      "x": 313.52,
      "y": 496.2,
      "id": 816
    },
    {
      "x": 731.08,
      "y": 975.44,
      "id": 817
    },
    {
      "x": 172.6,
      "y": 736.07,
      "id": 818
    },
    {
      "x": 477.28,
      "y": 526.49,
      "id": 819
    },
    {
      "x": 172.33,
      "y": 708.32,
      "id": 820
    },
    {
      "x": 544.24,
      "y": 628.4,
      "id": 821
    },
    {
      "x": 456.73,
      "y": 870.42,
      "id": 822
    },
    {
      "x": 90.31,
      "y": 96.05,
      "id": 823
    },
    {
      "x": 802.27,
      "y": 244.09,
      "id": 824
    },
    {
      "x": 570.62,
      "y": 723.82,
      "id": 825
    },
    {
      "x": 988.88,
      "y": 291.92,
      "id": 826
    },
    {
      "x": 853.57,
      "y": 309.23,
      "id": 827
    },
    {
      "x": 423.53,
      "y": 762.19,
      "id": 828
    },
    {
      "x": 390.53,
      "y": 552.19,
      "id": 829
    },
    {
      "x": 558.35,
      "y": 136.66,
      "id": 830
    },
    {
      "x": 27.47,
      "y": 541.14,
      "id": 831
    },
    {
      "x": 957.13,
      "y": 323.34,
      "id": 832
    },
    {
      "x": 591.78,
      "y": 733.48,
      "id": 833
    },
    {
      "x": 327.43,
      "y": 816.2,
      "id": 834
    },
    {
      "x": 507.33,
      "y": 7.68,
      "id": 835
    },
    {
      "x": 129.14,
      "y": 282.87,
      "id": 836
    },
    {
      "x": 110.2,
      "y": 357.86,
      "id": 837
    },
    {
      "x": 794.9,
      "y": 793.87,
      "id": 838
    },
    {
      "x": 66.22,
      "y": 540.34,
      "id": 839
    },
    {
      "x": 301.41,
      "y": 64.02,
      "id": 840
    },
    {
      "x": 222.13,
      "y": 368.98,
      "id": 841
    },
    {
      "x": 678.93,
      "y": 381.81,
      "id": 842
    },
    {
      "x": 122.18,
      "y": 927.58,
      "id": 843
    },
    {
      "x": 491.43,
      "y": 243.21,
      "id": 844
    },
    {
      "x": 388.0,
      "y": 860.09,
      "id": 845
    },
    {
      "x": 974.02,
      "y": 619.8,
      "id": 846
    },
    {
      "x": 904.67,
      "y": 413.59,
      "id": 847
    },
    {
      "x": 1.92,
      "y": 781.55,
      "id": 848
    },
    {
      "x": 656.19,
      "y": 975.73,
      "id": 849
    },
    {
      "x": 9.64,
      "y": 771.81,
      "id": 850
    },
    {
      "x": 531.07,
      "y": 331.28,
      "id": 851
    },
    {
      "x": 85.27,
      "y": 593.39,
      "id": 852
    },
    {
      "x": 771.52,
      "y": 726.5,
      "id": 853
    },
    {
      "x": 569.58,
      "y": 418.89,
      "id": 854
    },
    {
      "x": 395.64,
      "y": 159.68,
      "id": 855
    },
    {
      "x": 587.27,
      "y": 15.29,
      "id": 856
    },
    {
      "x": 282.21,
      "y": 671.97,
      "id": 857
    },
    {
      "x": 377.99,
      "y": 839.98,
      "id": 858
    },
    {
      "x": 355.57,
      "y": 235.47,
      "id": 859
    },
    {
      "x": 900.96,
      "y": 320.62,
      "id": 860
    },
    {
      "x": 811.86,
      "y": 766.46,
      "id": 861
    },
    {
      "x": 547.48,
      "y": 729.51,
      "id": 862
    },
    {
      "x": 568.67,
      "y": 386.08,
      "id": 863
    },
    {
      "x": 26.23,
      "y": 300.47,
      "id": 864
    },
    {
      "x": 507.23,
      "y": 973.27,
      "id": 865
    },
    {
      "x": 106.8,
      "y": 991.6,
      "id": 866
    },
    {
      "x": 98.49,
      "y": 73.42,
      "id": 867
    },
    {
      "x": 941.78,
      "y": 486.41,
      "id": 868
    },
    {
      "x": 770.71,
      "y": 120.51,
      "id": 869
    },
    {
      "x": 531.41,
      "y": 377.83,
      "id": 870
    },
    {
      "x": 431.02,
      "y": 815.37,
      "id": 871
    },
    {
      "x": 689.91,
      "y": 973.15,
      "id": 872
    },
    {
      "x": 405.67,
      "y": 45.51,
      "id": 873
    },
    {
      "x": 215.35,
      "y": 867.99,
      "id": 874
    },
    {
      "x": 142.1,
      "y": 939.21,
      "id": 875
    },
    {
      "x": 251.8,
      "y": 299.59,
      "id": 876
    },
    {
      "x": 552.7,
      "y": 812.18,
      "id": 877
    },
    {
      "x": 751.29,
      "y": 439.51,
      "id": 878
    },
    {
      "x": 365.27,
      "y": 736.23,
      "id": 879
    },
    {
      "x": 575.78,
      "y": 881.66,
      "id": 880
    },
    {
      "x": 724.72,
      "y": 513.11,
      "id": 881
    },
    {
      "x": 276.85,
      "y": 826.81,
      "id": 882
    },
    {
      "x": 824.12,
      "y": 397.46,
      "id": 883
    },
    {
      "x": 643.94,
      "y": 337.1,
      "id": 884
    },
    {
      "x": 428.73,
      "y": 702.54,
      "id": 885
    },
    {
      "x": 171.01,
      "y": 0.95,
      "id": 886
    },
    {
      "x": 198.27,
      "y": 45.08,
      "id": 887
    },
    {
      "x": 484.59,
      "y": 953.87,
      "id": 888
    },
    {
      "x": 455.42,
      "y": 680.1,
      "id": 889
    },
    {
      "x": 11.67,
      "y": 115.8,
      "id": 890
    },
    {
      "x": 643.7,
      "y": 83.12,
      "id": 891
    },
    {
      "x": 69.68,
      "y": 235.21,
      "id": 892
    },
    {
      "x": 854.56,
      "y": 646.78,
      "id": 893
    },
    {
      "x": 561.47,
      "y": 418.4,
      "id": 894
    },
    {
      "x": 620.99,
      "y": 296.45,
      "id": 895
    },
    {
      "x": 343.12,
      "y": 302.65,
      "id": 896
    },
    {
      "x": 660.48,
      "y": 6.8,
      "id": 897
    },
    {
      "x": 636.86,
      "y": 159.06,
      "id": 898
    },
    {
      "x": 642.52,
      "y": 959.82,
      "id": 899
    },
    {
      "x": 194.84,
      "y": 319.12,
      "id": 900
    },
    {
      "x": 91.65,
      "y": 716.83,
      "id": 901
    },
    {
      "x": 747.14,
      "y": 548.89,
      "id": 902
    },
    {
      "x": 681.72,
      "y": 62.21,
      "id": 903
    },
    {
      "x": 545.43,
      "y": 92.48,
      "id": 904
    },
    {
      "x": 293.61,
      "y": 597.01,
      "id": 905
    },
    {
      "x": 815.06,
      "y": 622.82,
      "id": 906
    },
    {
      "x": 668.06,
      "y": 686.37,
      "id": 907
    },
    {
      "x": 912.87,
      "y": 229.03,
      "id": 908
    },
    {
      "x": 976.47,
      "y": 432.16,
      "id": 909
    },
    {
      "x": 504.64,
      "y": 730.41,
      "id": 910
    },
    {
      "x": 152.5,
      "y": 862.31,
      "id": 911
    },
    {
      "x": 29.67,
      "y": 37.52,
      "id": 912
    },
    {
      "x": 411.54,
      "y": 517.02,
      "id": 913
    },
    {
      "x": 52.68,
      "y": 572.74,
      "id": 914
    },
    {
      "x": 602.57,
      "y": 515.65,
      "id": 915
    },
    {
      "x": 127.2,
      "y": 628.59,
      "id": 916
    },
    {
      "x": 731.55,
      "y": 535.95,
      "id": 917
    },
    {
      "x": 217.26,
      "y": 660.01,
      "id": 918
    },
    {
      "x": 397.53,
      "y": 238.93,
      "id": 919
    },
    {
      "x": 412.32,
      "y": 550.03,
      "id": 920
    },
    {
      "x": 46.0,
      "y": 857.93,
      "id": 921
    },
    {
      "x": 312.03,
      "y": 485.98,
      "id": 922
    },
    {
      "x": 550.08,
      "y": 102.75,
      "id": 923
    },
    {
      "x": 348.63,
      "y": 290.57,
      "id": 924
    },
    {
      "x": 961.63,
      "y": 7.59,
      "id": 925
    },
    {
      "x": 905.22,
      "y": 3.4,
      "id": 926
    },
    {
      "x": 395.4,
      "y": 972.96,
      "id": 927
    },
    {
      "x": 652.97,
      "y": 491.59,
      "id": 928
    },
    {
      "x": 577.56,
      "y": 567.52,
      "id": 929
    },
    {
      "x": 449.44,
      "y": 903.38,
      "id": 930
    },
    {
      "x": 697.4,
      "y": 358.75,
      "id": 931
    },
    {
      "x": 447.74,
      "y": 764.58,
      "id": 932
    },
    {
      "x": 983.37,
      "y": 844.91,
      "id": 933
    },
    {
      "x": 607.18,
      "y": 115.77,
      "id": 934
    },
    {
      "x": 480.87,
      "y": 44.83,
      "id": 935
    },
    {
      "x": 984.76,
      "y": 471.1,
      "id": 936
    },
    {
      "x": 464.58,
      "y": 709.57,
      "id": 937
    },
    {
      "x": 936.07,
      "y": 300.71,
      "id": 938
    },
    {
      "x": 161.87,
      "y": 511.36,
      "id": 939
    },
    {
      "x": 433.36,
      "y": 736.19,
      "id": 940
    },
    {
      "x": 726.36,
      "y": 123.78,
      "id": 941
    },
    {
      "x": 36.27,
      "y": 956.68,
      "id": 942
    },
    {
      "x": 68.88,
      "y": 810.64,
      "id": 943
    },
    {
      "x": 22.57,
      "y": 86.24,
      "id": 944
    },
    {
      "x": 958.79,
      "y": 556.63,
      "id": 945
    },
    {
      "x": 609.6,
      "y": 162.19,
      "id": 946
    },
    {
      "x": 946.28,
      "y": 781.96,
      "id": 947
    },
    {
      "x": 971.11,
      "y": 993.43,
      "id": 948
    },
    {
      "x": 494.63,
      "y": 906.16,
      "id": 949
    },
    {
      "x": 371.55,
      "y": 623.62,
      "id": 950
    },
    {
      "x": 221.86,
      "y": 897.52,
      "id": 951
    },
    {
      "x": 45.93,
      "y": 532.93,
      "id": 952
    },
    {
      "x": 104.78,
      "y": 720.34,
      "id": 953
    },
    {
      "x": 222.88,
      "y": 405.87,
      "id": 954
    },
    {
      "x": 198.19,
      "y": 714.8,
      "id": 955
    },
    {
      "x": 118.46,
      "y": 344.8,
      "id": 956
    },
    {
      "x": 211.68,
      "y": 569.34,
      "id": 957
    },
    {
      "x": 438.45,
      "y": 593.61,
      "id": 958
    },
    {
      "x": 852.47,
      "y": 836.74,
      "id": 959
    },
    {
      "x": 341.95,
      "y": 272.21,
      "id": 960
    },
    {
      "x": 484.04,
      "y": 29.98,
      "id": 961
    },
    {
      "x": 453.67,
      "y": 286.74,
      "id": 962
    },
    {
      "x": 913.79,
      "y": 452.25,
      "id": 963
    },
    {
      "x": 80.54,
      "y": 962.78,
      "id": 964
    },
    {
      "x": 255.16,
      "y": 605.97,
      "id": 965
    },
    {
      "x": 293.5,
      "y": 63.08,
      "id": 966
    },
    {
      "x": 533.85,
      "y": 149.63,
      "id": 967
    },
    {
      "x": 579.74,
      "y": 543.61,
      "id": 968
    },
    {
      "x": 735.45,
      "y": 803.5,
      "id": 969
    },
    {
      "x": 844.39,
      "y": 253.22,
      "id": 970
    },
    {
      "x": 500.62,
      "y": 512.28,
      "id": 971
    },
    {
      "x": 468.27,
      "y": 411.99,
      "id": 972
    },
    {
      "x": 594.9,
      "y": 46.55,
      "id": 973
    },
    {
      "x": 451.32,
      "y": 87.77,
      "id": 974
    },
    {
      "x": 909.06,
      "y": 444.18,
      "id": 975
    },
    {
      "x": 111.54,
      "y": 10.94,
      "id": 976
    },
    {
      "x": 339.63,
      "y": 781.46,
      "id": 977
    },
    {
      "x": 705.71,
      "y": 45.4,
      "id": 978
    },
    {
      "x": 207.95,
      "y": 934.44,
      "id": 979
    },
    {
      "x": 939.74,
      "y": 703.51,
      "id": 980
    },
    {
      "x": 248.2,
      "y": 679.82,
      "id": 981
    },
    {
      "x": 80.69,
      "y": 498.27,
      "id": 982
    },
    {
      "x": 586.14,
      "y": 791.97,
      "id": 983
    },
    {
      "x": 531.04,
      "y": 316.07,
      "id": 984
    },
    {
      "x": 308.19,
      "y": 376.57,
      "id": 985
    },
    {
      "x": 962.16,
      "y": 387.32,
      "id": 986
    },
    {
      "x": 917.53,
      "y": 938.01,
      "id": 987
    },
    {
      "x": 273.51,
      "y": 374.41,
      "id": 988
    },
    {
      "x": 526.75,
      "y": 161.98,
      "id": 989
    },
    {
      "x": 270.24,
      "y": 171.15,
      "id": 990
    },
    {
      "x": 18.82,
      "y": 13.25,
      "id": 991
    },
    {
      "x": 350.86,
      "y": 498.46,
      "id": 992
    },
    {
      "x": 95.16,
      "y": 970.64,
      "id": 993
    },
    {
      "x": 212.8,
      "y": 33.42,
      "id": 994
    },
    {
      "x": 193.2,
      "y": 269.17,
      "id": 995
    },
    {
      "x": 452.34,
      "y": 733.4,
      "id": 996
    },
    {
      "x": 374.04,
      "y": 862.63,
      "id": 997
    },
    {
      "x": 326.84,
      "y": 324.69,
      "id": 998
    },
    {
      "x": 150.44,
      "y": 625.03,
      "id": 999
    }
  ]
}